dlite.py
string_comparison.py
string_comparison-1.1.0.dist-info/LICENSE.md
string_comparison-1.1.0.dist-info/METADATA
string_comparison-1.1.0.dist-info/WHEEL
string_comparison-1.1.0.dist-info/top_level.txt
string_comparison-1.1.0.dist-info/RECORD
