Metadata-Version: 2.1
Name: string-comparison
Version: 1.1.0
Summary: Utility to assist with string comparisons.
Home-page: https://github.com/bbelyeu/string_comparison/
Author: Brad Belyeu
Author-email: bradley.belyeu@life.church
License: MIT
Download-URL: https://github.com/bbelyeu/string_comparison/archive/1.1.0.zip
Keywords: unicode
Platform: any
Classifier: Intended Audience :: Developers
Classifier: License :: OSI Approved :: MIT License
Classifier: Operating System :: OS Independent
Classifier: Programming Language :: Python
Classifier: Programming Language :: Python :: 3
Requires-Python: >3.7.0
